jrti_game/__init__.py
jrti_game/__main__.py
jrti_game/adjuster.py
jrti_game/bug.py
jrti_game/coords.py
jrti_game/data.py
jrti_game/end.py
jrti_game/fallback.py
jrti_game/flippable.py
jrti_game/game.py
jrti_game/instructions.py
jrti_game/key_names.py
jrti_game/state.py
jrti_game/text.py
jrti_game/tool.py
jrti_game/util.py
jrti_game/data/instructions.txt
jrti_game/data/spritesheet.png
jrti_game/data/font/Itim-Regular.ttf
jrti_game/data/font/OFL.txt
jrti_game-1.0.3.dist-info/LICENSE
jrti_game-1.0.3.dist-info/LICENSES
jrti_game-1.0.3.dist-info/METADATA
jrti_game-1.0.3.dist-info/WHEEL
jrti_game-1.0.3.dist-info/entry_points.txt
jrti_game-1.0.3.dist-info/top_level.txt
jrti_game-1.0.3.dist-info/RECORD
